[
  {
    "id":"g1",
    "name":"حضانات مستشفي تلا المركزي",
    "phone":"0483787955",
    "address":"ش السادات، مدينة تلا، مركز تلا، المنوفية",
    "location":"https://goo.gl/maps/Ypy7W4j2urt6mqn57",
    "late":30.68454975832983,
    "long":30.95028490014212,
    "image":["https://i.pinimg.com/564x/3e/d7/b8/3ed7b87af4592207a60f7abc079059f3.jpg","https://i.pinimg.com/564x/29/6f/41/296f418e65cd67b9ae148555b711d1b9.jpg","https://i.pinimg.com/236x/6e/50/ff/6e50ff91b9f23cac40932535a65473b1.jpg"],
    "icon_name":"0xf0f8",
    "color":"#98AFC7",
    "email":"tala@gmail.com",
    "password":"123456789",
    "profile":"https://i.pinimg.com/564x/3e/d7/b8/3ed7b87af4592207a60f7abc079059f3.jpg",
    "type":"governmentHospital",
    "availability":"true",
    "open":"24 hours",
    "uid": "OHfVCiWQyyP7G2ZYFG4BLssTZNt2"
  },
  {
    "id":"g2",
    "name":"حضانات مستشفي بركة السبع",
    "phone":"لا يوجد",
    "address":"طريق هورين - البر الشرقى, بجوار صيدلية د على امين",
    "location":"https://goo.gl/maps/3uVZdf8A2xJY1Xtz8",
    "late":30.635478259074432,
    "long":31.090294810786844,
    "image":["https://i.pinimg.com/236x/79/10/fb/7910fb9997a023f81bb5049376d6452c.jpg","https://i.pinimg.com/564x/77/9a/b1/779ab1cb0c6bae45eaa3c9dc1db269b3.jpg","https://i.pinimg.com/564x/83/66/fa/8366fa404d249cef412c32dd0362f05e.jpg"],
    "icon_name":"0xf0f8",
    "color":"#98AFC7",
    "email":"berket@gmail.com",
    "password":"123456789",
    "profile":"https://i.pinimg.com/236x/79/10/fb/7910fb9997a023f81bb5049376d6452c.jpg",
    "type":"governmentHospital",
    "availability":"true",
    "open":"24 hours",
    "uid": "1ntjkXS7i4eBQwXhpHRU3UG39ln1"
  },
  {
    "id":"g3",
    "name":"حضانات مستشفي شبين الكوم التعليمي",
    "phone":"0482221277",
    "address":"ش جمال عبد الناصر, بجوار مجمع الكليات",
    "location":"https://goo.gl/maps/FoqMnL15z3ZRrknTA",
    "late":30.57447605668898,
    "long":31.01209122959227,
    "image":["https://i.pinimg.com/564x/83/66/fa/8366fa404d249cef412c32dd0362f05e.jpg","https://i.pinimg.com/564x/fe/bf/d8/febfd89c33f022fe62dc4259df6b3c36.jpg","https://i.pinimg.com/564x/ab/55/6f/ab556fb029b77967d2c2c8aa8a558cf5.jpg"],
    "icon_name":"0xf0f8",
    "color":"#98AFC7",
    "email":"sheben@gmail.com",
    "password":"123456789",
    "profile":"https://i.pinimg.com/564x/83/66/fa/8366fa404d249cef412c32dd0362f05e.jpg",
    "type":"governmentHospital",
    "availability":"true",
    "open":"24 hours",
    "uid": "hi4mFGcjzAZQnCnfIZ0ThztBC2Q2"



  },
  {
    "id":"g4",
    "name":"حضانات مستشفي قويسنا المركزي",
    "phone":"0482579460",
    "address":"مستشفى، طريق القاهرة اسكندرية الزراعى بجوار، مركز قويسنا، المنوفية",
    "location":"https://goo.gl/maps/4Zn1pWi7JDPqx5w69",
    "late":30.552612178908394,
    "long":31.138998129589098,
    "image":["https://i.pinimg.com/564x/18/7d/bc/187dbc546be663b111a1d027317b708b.jpg","https://i.pinimg.com/564x/18/7d/bc/187dbc546be663b111a1d027317b708b.jpg","https://i.pinimg.com/564x/5e/e4/c3/5ee4c39ab36e934f472709fbc7f9809e.jpg"],
    "icon_name":"0xf0f8",
    "color":"#98AFC7",
    "email":"eousna@gmail.com",
    "password":"123456789",
    "profile":"https://i.pinimg.com/564x/18/7d/bc/187dbc546be663b111a1d027317b708b.jpg",
    "type":"governmentHospital",
    "availability":"true",
    "open":"24 hours",
    "uid": "XtGA1Av0DWgLbvUSC5ucKQNo5sw1"

  },
  {
    "id":"g5",
    "name":"حضانات مستشفى الباجور",
    "phone":"0483882935",
    "address":"طريق الباجور منوف ، الباجور ، المنوفية",
    "location":"https://goo.gl/maps/YyChhKqWqc8hYoD67",
    "late":30.43277976272684,
    "long":31.02925135452893,
    "image":["https://i.pinimg.com/564x/51/b8/9b/51b89bd840e87841931880fd62378766.jpg","https://i.pinimg.com/564x/4e/e1/6a/4ee16aa64ee218d69b88ef8aba5ffb95.jpg","https://i.pinimg.com/564x/51/b8/9b/51b89bd840e87841931880fd62378766.jpg"],
    "icon_name":"0xf0f8",
    "color":"#98AFC7",
    "email":"elbagor@gmail.com",
    "password":"123456789",
    "profile":"https://i.pinimg.com/564x/51/b8/9b/51b89bd840e87841931880fd62378766.jpg",
    "type":"governmentHospital",
    "availability":"true",
    "open":"24 hours",
    "uid": "dZnBs4T3MBP0gdk94cpNcltSaFE3"
  },
  {
    "id":"g6",
    "name":"حضانات مستشفي السادات المركزي",
    "phone":"0482600047",
    "address":"شارع الحسن بن على, السادات، المنوفية",
    "location":"https://goo.gl/maps/ZUmjkZm1Y4AALcWH9",
    "late":30.367190621900548,
    "long":30.50598233600393,
    "image":["https://i.pinimg.com/564x/1b/19/72/1b1972a8c1bef1011691ef13a5296c58.jpg","https://i.pinimg.com/564x/1b/19/72/1b1972a8c1bef1011691ef13a5296c58.jpg","https://i.pinimg.com/564x/70/8a/f1/708af1ce4bda6a238df412ac5d90c422.jpg"],
    "icon_name":"0xf0f8",
    "color":"#98AFC7",
    "email":"elsadat@gmail.com",
    "password":"123456789",
    "profile":"https://i.pinimg.com/564x/1b/19/72/1b1972a8c1bef1011691ef13a5296c58.jpg",
    "type":"governmentHospital",
    "availability":"true",
    "open":"24 hours",
    "uid": "NPvsidly4gZLpIINBgeUbMetGDu1"
  },
  {
    "id":"g7",
    "name":"حضانات مستشفي منوف العام",
    "phone":"0483660012",
    "address":"ش الجيش منوف المنوفية",
    "location":"https://goo.gl/maps/AnXQWZ2UNULqz49p8",
    "late":30.471802453750183,
    "long":30.927749047034624,
    "image":["https://i.pinimg.com/564x/8c/ce/9e/8cce9e859f02bae8f660821a0ffba3a3.jpg","https://i.pinimg.com/564x/be/c7/c8/bec7c8d25b7a98bab83a2d790e297ef7.jpg","https://i.pinimg.com/564x/18/fa/c1/18fac12d2588a9dc2602e2614069f5c5.jpg"],
    "icon_name":"0xf0f8",
    "color":"#98AFC7",
    "email":"monof@gmail.com",
    "password":"123456789",
    "profile":"https://i.pinimg.com/564x/8c/ce/9e/8cce9e859f02bae8f660821a0ffba3a3.jpg",
    "type":"governmentHospital",
    "availability":"true",
    "open":"24 hours",
    "uid": "3UBG8sPiaXYFgg8DZdnakMsuUxx2"
  },
  {
    "id":"g8",
    "name":"حضانات مستشفي اشمون العام",
    "phone":"0483448499",
    "address":"طريق سنتريس اشمون محافظة المنوفية",
    "location":"https://goo.gl/maps/fQdT2om7EwGfZC8s8",
    "late":30.295877073584915,
    "long":30.988961800139478,
    "image":["https://i.pinimg.com/564x/97/c4/1f/97c41f95d9473005240dbf870878556b.jpg","https://i.pinimg.com/564x/f8/dd/1a/f8dd1ad308858e82890b536323fa5b6d.jpg","https://i.pinimg.com/564x/3e/fb/0b/3efb0b5202ed48ebab4cee9d6cbbf96a.jpg"],
    "icon_name":"0xf0f8",
    "color":"#98AFC7",
    "email":"ashmon@gmail.com",
    "password":"123456789",
    "profile":"https://i.pinimg.com/564x/97/c4/1f/97c41f95d9473005240dbf870878556b.jpg",
    "type":"governmentHospital",
    "availability":"true",
    "open":"24 hours",
    "uid": "Px4mNxQ6PqSyLP14Juu9HfFysfz1"
  },
  {
    "id":"g9",
    "name":"حضانات مستشفي سرس الليان المركزي",
    "phone":"0483351431",
    "address":"ش بور سعيد، مدينة سرس الليانة، مركز منوف، المنوفية",
    "location":"https://goo.gl/maps/2X9agKCCtFGgWzQ46",
    "late":30.442403319473,
    "long":30.960883806670832,
    "image":["https://i.pinimg.com/564x/f8/dd/1a/f8dd1ad308858e82890b536323fa5b6d.jpg","https://i.pinimg.com/736x/4e/2d/e6/4e2de62e5eb956b23451239b7eaf761a.jpg","https://i.pinimg.com/564x/c7/bf/57/c7bf5722aecc45afe3534adfc6d466b2.jpg"],
    "icon_name":"0xf0f8",
    "color":"#98AFC7",
    "email":"sers@gmail.com",
    "password":"123456789",
    "profile":"https://i.pinimg.com/564x/f8/dd/1a/f8dd1ad308858e82890b536323fa5b6d.jpg",
    "type":"governmentHospital",
    "availability":"true",
    "open":"24 hours",
    "uid": "vzwEoBBqz7aNIMu8xkz5YrXyUrQ2"
  },
  {
    "id":"g10",
    "name":"حضانات مستشفي الشهداء المركزي",
    "phone":"0482740649",
    "address":"ش بورسعيد الشهداء المنوفية",
    "location":"https://goo.gl/maps/HoPFhz9i8zZdWqJM7",
    "late":30.596665257019122,
    "long":30.904721547034626,
    "image":["https://i.pinimg.com/564x/26/26/65/262665f09a3e8548ded4556b1f82f43f.jpg","https://i.pinimg.com/564x/c7/bf/57/c7bf5722aecc45afe3534adfc6d466b2.jpg","https://i.pinimg.com/564x/f9/6d/d3/f96dd3364f9b7a6ebeb370d9c8ece086.jpg"],
    "icon_name":"0xf0f8",
    "color":"#98AFC7",
    "email":"elshohada@gmail.com",
    "password":"123456789",
    "profile":"https://i.pinimg.com/564x/26/26/65/262665f09a3e8548ded4556b1f82f43f.jpg",
    "type":"governmentHospital",
    "availability":"true",
    "open":"24 hours",
    "uid": "frd4V81geBOv1hUzzrNrZwdnBi92"
  },
  {
    "id":"g11",
    "name":"مركز تبارك للأطفال",
    "phone":"0220674297",
    "address":"سليم الاول، منشية التحرير، قسم عين شمس، محافظة القاهرة",
    "location":"https://goo.gl/maps/uVVdbn8Sbs9YikWd7",
    "late":30.118643587397063,
    "long":31.320736076168018,
    "image":["https://i.pinimg.com/564x/14/9b/70/149b705fbc9418246191d34dc5022b12.jpg","https://i.pinimg.com/564x/10/f6/10/10f610f69c87a3880a5046c4e45dd54a.jpg","https://i.pinimg.com/564x/57/ec/12/57ec12211b56a6d2136de63027634e83.jpg"],
    "icon_name":"0xf0f8",
    "color":"#98AFC7",
    "email":"tabarak@gmail.com",
    "password":"123456789",
    "profile":"https://i.pinimg.com/564x/14/9b/70/149b705fbc9418246191d34dc5022b12.jpg",
    "type":"governmentHospital",
    "availability":"true",
    "open":"24 hours",
    "uid": "uPrgmaAvQxRElg9yZuTGBG8t9Cp2"
  },
  {
    "id":"g12",
    "name":"حضانات مستشفيات جامعة أسوان",
    "phone":"0972428625",
    "address":"قصر الهجير - اول اسوان، أسوان",
    "location":"https://goo.gl/maps/Gve6Ao4mCqiuvAnB9",
    "late":24.086609700017853,
    "long":32.9078500086466,
    "image":["https://i.pinimg.com/564x/5d/62/2a/5d622ac357018711a275f72656c95af8.jpg","https://i.pinimg.com/564x/02/2b/c3/022bc3387665b76d11aab3faee3175cf.jpg","https://i.pinimg.com/564x/06/c9/36/06c9368547acfdb19ea835ef7f67f1a2.jpg"],
    "icon_name":"0xf0f8",
    "color":"#98AFC7",
    "email":"aswan@gmail.com",
    "password":"123456789",
    "profile":"https://i.pinimg.com/564x/5d/62/2a/5d622ac357018711a275f72656c95af8.jpg",
    "type":"governmentHospital",
    "availability":"true",
    "open":"24 hours",
    "uid": "9ChZsVQLiqPxb6z5X9OeWka9eED2"
  },
  {
    "id":"g13",
    "name":"حضانات مستشفى رأس سدر المركزي",
    "phone":"#",
    "address":"راس سدر،، جنوب سيناء",
    "location":"https://goo.gl/maps/Gk2reL29ni6kWqyB8",
    "late":29.589438341196352,
    "long":32.71089990300442,
    "image":["https://i.pinimg.com/564x/4d/c9/01/4dc9014f2983e60f64febf2d21690530.jpg","https://i.pinimg.com/564x/12/c0/8c/12c08cdc9a23dca1e652b15afc59d04d.jpg","https://i.pinimg.com/564x/e2/58/7c/e2587c93f76aff9a7e2cc70710d77f5a.jpg"],
    "icon_name":"0xf0f8",
    "color":"#98AFC7",
    "email":"ras_sedr@gmail.com",
    "password":"123456789",
    "profile":"https://i.pinimg.com/564x/4d/c9/01/4dc9014f2983e60f64febf2d21690530.jpg",
    "type":"governmentHospital",
    "availability":"true",
    "open":"24 hours",
    "uid": "TvrH9q5K0wVt3Igy1BzX7VX8A4r2"
  },
  {
    "id":"g14",
    "name":"حضانات مستشفى إيزيس التخصصي للنساء والولادة",
    "phone":"0952300039",
    "address":"ش المصالح الحكومية، مدينة البياضية، مركز الأقصر، محافظة الأقصر",
    "location":"https://goo.gl/maps/9VTy9ioVKMrHVp3G8",
    "late":25.66443607268849,
    "long":32.63135983254056,
    "image":["https://i.pinimg.com/564x/d8/a0/b0/d8a0b021c7af3b3b675b1ebfdb914dde.jpg","https://i.pinimg.com/736x/6c/de/1c/6cde1c25bc330c38ea7c5ce3abb6d640.jpg","https://i.pinimg.com/564x/a2/42/e7/a242e7467e062a831d67f534748813e0.jpg"],
    "icon_name":"0xf0f8",
    "color":"#98AFC7",
    "email":"eyzes@gmail.com",
    "password":"123456789",
    "profile":"https://i.pinimg.com/564x/d8/a0/b0/d8a0b021c7af3b3b675b1ebfdb914dde.jpg",
    "type":"governmentHospital",
    "availability":"true",
    "open":"24 hours",
    "uid": "pqapHw7YJYWozPpMEzQX0BdHTD13"
  },
  {
    "id":"g15",
    "name":"حضانات مستشفي الإيمان للأطفال",
    "phone":"#",
    "address":"قسم بني سويف، مركز بنى سويف، محافظة بني سويف",
    "location":"https://goo.gl/maps/Z3J6DYv8m1TdaErX6",
    "late":29.07989461718878,
    "long":31.102586532464436,
    "image":["https://i.pinimg.com/736x/6c/de/1c/6cde1c25bc330c38ea7c5ce3abb6d640.jpg","https://i.pinimg.com/564x/25/fa/5d/25fa5dfc04a351c7d87617bcd09b0f0d.jpg","https://i.pinimg.com/564x/1a/c2/c5/1ac2c5022d696eb7b5d1d79c04564253.jpg"],
    "icon_name":"0xf0f8",
    "color":"#98AFC7",
    "email":"eleman@gmail.com",
    "password":"123456789",
    "profile":"https://i.pinimg.com/736x/6c/de/1c/6cde1c25bc330c38ea7c5ce3abb6d640.jpg",
    "type":"governmentHospital",
    "availability":"true",
    "open":"24 hours",
    "uid": "jV73Fi1BhSgucXD0BUuCFK2fWMr1"
  },

  {
    "id":"c1",
    "name":"مستشفى الجمعية الشرعية للاطفال المبتسرين وحديثى الولادةبشبين الكوم",
    "phone":"0482260099",
    "address":"ش محمود شاهين-شبين الكوم-المنوفية",
    "location":"https://goo.gl/maps/joBxszZMnacmaYMV6",
    "late":30.565890884222636,
    "long":31.00324154960695,
    "image":["https://i.pinimg.com/564x/ab/55/6f/ab556fb029b77967d2c2c8aa8a558cf5.jpg","https://i.pinimg.com/564x/5e/aa/88/5eaa882cec59a4ff67d9e8f1c8e8b43f.jpg","https://i.pinimg.com/564x/b5/df/d5/b5dfd5e9afbf54a88a04a3991833247b.jpg"],
    "icon_name":"0xf80e",
    "color":"#438D80",
    "email":"elshareya@gmail.com",
    "password":"123456789",
    "profile":"https://i.pinimg.com/564x/ab/55/6f/ab556fb029b77967d2c2c8aa8a558cf5.jpg",
    "type": "charityCenter",
    "availability":"true",
    "open":"24 hours",
    "uid": "VU50xkOmdINlFdjdraf1Lp4B2Wa2"
  },
  {
    "id":"c2",
    "name":"مستشفى الجمعية الشرعية للاطفال المبتسرين وحديثى الولادة(فرع الباجور)",
    "phone":"0483886355",
    "address":"ش المرور متفرع من شارع بنها-الباجور-المنوفية",
    "location":"https://goo.gl/maps/mpzAqYCJo7SvcYiHA",
    "late":30.427188341216844,
    "long":31.04417977238148,
    "image":["https://i.pinimg.com/564x/a6/71/26/a671260636a9f0a35684001c42c46b39.jpg","https://i.pinimg.com/564x/50/af/bd/50afbdf04821795114b56fcbe6a7a0ea.jpg","https://i.pinimg.com/564x/33/3a/25/333a25d46f3d25b34412dfdbc45d8048.jpg"],
    "icon_name":"0xf80e",
    "color":"#438D80",
    "email":"elgameya_elshareya@gmail.com",
    "password":"123456789",
    "profile":"https://i.pinimg.com/564x/a6/71/26/a671260636a9f0a35684001c42c46b39.jpg",
    "type": "charityCenter",
    "availability":"true",
    "open":"24 hours",
    "uid": "7V6Oep2McXWqAsTGxeyjSSD48CD2"
  },
  {
    "id":"c3",
    "name":"مستشفى الجمعية الشرعية للاطفال المبتسرين بمصر الجديدة",
    "phone":"0226908719" ,
    "address":"مساكن الماظة-ش الشهيد اسماعيل موسي-الماظة-مصر الجديدة-القاهرة",
    "location":"https://goo.gl/maps/iJnAX9VCaWBzM7rF9",
    "late":30.082709549422997,
    "long":31.354504329167526,
    "image":["https://i.pinimg.com/564x/de/fd/62/defd62c203174903409310bdf5b1cd4e.jpg","https://i.pinimg.com/564x/21/74/0e/21740e708cdff597d49a0594eaed1081.jpg","https://i.pinimg.com/564x/c7/7a/00/c77a0014160f2d92ef083d72c209efcb.jpg"],
    "icon_name":"0xf80e",
    "color":"#438D80",
    "email":"elshareya1@gmail.com",
    "password":"123456789",
    "profile":"https://i.pinimg.com/564x/de/fd/62/defd62c203174903409310bdf5b1cd4e.jpg",
    "type": "charityCenter",
    "availability":"true",
    "open":"24 hours",
    "uid": "h1shrKc69wQETOC9mKJYynLF3JT2"
  },
  {
    "id":"c4",
    "name":"مستشفى الجمعية الشرعية للاطفال المبتسرين(فرع الحي السادس القاهرة)",
    "phone":"0222634655",
    "address":"ش المخيم الدائم-الحي السادس-مدينة نصر-القاهرة",
    "location":"https://goo.gl/maps/jTeuHmU9CoPD1BUEA",
    "late":30.047870336127698,
    "long":31.313576609777417,
    "image":["https://i.pinimg.com/564x/7c/43/bb/7c43bb05e0ea99c3c37719ab3b1da161.jpg","https://i.pinimg.com/736x/d2/13/29/d21329be65fec6bbb80339d408952461.jpg","https://i.pinimg.com/564x/5c/64/4b/5c644bd37ffede2631ed97afc99dafee.jpg"],
    "icon_name":"0xf80e",
    "color":"#438D80",
    "email":"elshareya2@gmail.com",
    "password":"123456789",
    "profile":"https://i.pinimg.com/564x/7c/43/bb/7c43bb05e0ea99c3c37719ab3b1da161.jpg",
    "type":"charityCenter",
    "availability":"true",
    "open":"24 hours",
    "uid": "IpsdCSDW7fVp4N75ogOS3pytohB2"
  },
  {
    "id":"c5",
    "name":"مستشفى الجمعية الشرعية للاطفال المبتسرين بعين شمس",
    "phone":"0222950283",
    "address":"ش 127 متفرع من ش مسجد الوطنية-عين شمس-القاهرة",
    "location":"https://goo.gl/maps/dAyxyNYffSfC6wy57",
    "late":30.136933158179918,
    "long":31.367915865832078,
    "image":["https://i.pinimg.com/564x/fc/aa/68/fcaa683ece54459cfbb3c9bde9afa002.jpg","https://i.pinimg.com/564x/5b/fd/c9/5bfdc9d5307dd27126eaf53c9c73911d.jpg","https://i.pinimg.com/564x/77/c1/58/77c1581eba42b94cbe7822a50b0cc7b7.jpg"],
    "icon_name":"0xf80e",
    "color":"#438D80",
    "email":"elshareya3@gmail.com",
    "password":"123456789",
    "profile":"https://i.pinimg.com/564x/fc/aa/68/fcaa683ece54459cfbb3c9bde9afa002.jpg",
    "type":"charityCenter",
    "availability":"true",
    "open":"24 hours",
    "uid": "soVwlvt4eMROKpNJ2y4LMVgAp6n2"
  },
  {
    "id":"c6",
    "name":"مستشفى الجمعية الشرعية للاطفال المبتسرين بشبرا الخيمة",
    "phone":"0244475361",
    "address":"ش الصوه-شبرا الخيمة-القليوبية",
    "location":"https://goo.gl/maps/YnniPDRDaWxhXB8P6",
    "late":30.123384153949665,
    "long":31.260928316343094,
    "image":["https://i.pinimg.com/564x/41/93/a6/4193a635879db28a42794e0ccf10d439.jpg","https://i.pinimg.com/236x/86/5e/f5/865ef5dfb9b951d6bd7a65cc2b47393e.jpg","https://i.pinimg.com/236x/50/47/6f/50476f0787b3218e9dc8db8fd6b39317.jpg"],
    "icon_name":"0xf80e",
    "color":"#438D80",
    "email":"elshareya4@gmail.com",
    "password":"123456789",
    "profile":"https://i.pinimg.com/564x/41/93/a6/4193a635879db28a42794e0ccf10d439.jpg",
    "type":"charityCenter",
    "availability":"true",
    "open":"24 hours",
    "uid": "nBMZqTQV6ERHo6t3dGaIFqwd3xG2"
  },
  {
    "id":"c7",
    "name":"مستشفى الجمعية الشرعية للاطفال المبتسرين وحديثى الولادةبكفر الزيات",
    "phone":"0453443680 " ,
    "address":"جمال عبد الناصر، مدينة كفر الزيات، كفر الزيات،، مركز كفر الزيات، الغربية",
    "location":"https://goo.gl/maps/6sjqZdtpXDW2pQkS7",
    "late":30.82367640849772,
    "long":30.81452173674383,
    "image":["https://i.pinimg.com/236x/1a/6e/76/1a6e76f7ab16e6fc9d9b67abce7921ff.jpg","https://i.pinimg.com/564x/72/e5/01/72e50139d7f08642fa92f6f2de6248a1.jpg","https://i.pinimg.com/236x/12/cc/ac/12ccacb11ab30cd186d936dc86b61caf.jpg"],
    "icon_name":"0xf80e",
    "color":"#438D80",
    "email":"elshareya5@gmail.com",
    "password":"123456789",
    "profile":"https://i.pinimg.com/236x/1a/6e/76/1a6e76f7ab16e6fc9d9b67abce7921ff.jpg",
    "type":"charityCenter",
    "availability":"true",
    "open":"24 hours",
    "uid": "n58cQqM6rZVB8h0xyuLgNOEgpXF2"
  },
  {
    "id":"c8",
    "name":"مستشفى الجمعية الشرعية للاطفال المبتسرين بفرع اسكندرية",
    "phone":"033090565",
    "address":"ش مسد الطيار-البيطاش-الاسكندرية-امام حي العجمي",
    "location":"https://goo.gl/maps/gedKW7BG9FxcL9MA8",
    "late":31.11823146484606,
    "long":29.792446829592663,
    "image":["https://i.pinimg.com/236x/53/08/ab/5308ab3477d13ae76c9c6400c45e5d04.jpg","https://i.pinimg.com/236x/a1/1f/e8/a11fe836546557b75b75712ca506a73a.jpg","https://i.pinimg.com/236x/96/d5/7c/96d57cb12e5fbc29176bf6457c6a0a29.jpg"],
    "icon_name":"0xf80e",
    "color":"#438D80",
    "email":"elshareya6@gmail.com",
    "password":"123456789",
    "profile":"https://i.pinimg.com/236x/53/08/ab/5308ab3477d13ae76c9c6400c45e5d04.jpg",
    "type":"charityCenter",
    "availability":"true",
    "open":"24 hours",
    "uid": "9nWt2lhavtRfR119GZt0lOSuRU53"
  },
  {
    "id":"c9",
    "name":"مستشفى الجمعية الشرعية للاطفال المبتسرين فرع كفر الشيخ",
    "phone":"0473215546 " ,
    "address":"ش النقراشي-وسط البلد-كفرالشيخ",
    "location":"https://goo.gl/maps/Z5XjNLn6TEYLaEcX6",
    "late":31.110881790628284,
    "long":30.938188161222953,
    "image":["https://i.pinimg.com/236x/4c/de/84/4cde84dbe8422d9524f2ed7115233ec4.jpg","https://i.pinimg.com/236x/87/0f/0b/870f0b924d3991308eba008b91cb74c3.jpg","https://i.pinimg.com/236x/ee/99/23/ee99233bfd46a30e70091bc5b66a293d.jpg"],
    "icon_name":"0xf80e",
    "color":"#438D80",
    "email":"elshareya7@gmail.com",
    "password":"123456789",
    "profile":"https://i.pinimg.com/236x/4c/de/84/4cde84dbe8422d9524f2ed7115233ec4.jpg",
    "type":"charityCenter",
    "availability":"true",
    "open":"24 hours",
    "uid": "DHdaAdwAMCX562fVJFMpeisEbhV2"
  },
  {
    "id":"c10",
    "name":"مستشفى الجمعية الشرعية للاطفال المبتسرين بفرع سوهاج",
    "phone":"0932303310",
    "address":"مدينة العرائس-نجع مطرود-سوهاج-سوهاج",
    "location":"https://goo.gl/maps/hPoKtu3CrQH3Eu888",
    "late":26.560302184612294,
    "long":31.69181475655312,
    "image":["https://i.pinimg.com/236x/6a/50/d9/6a50d95c92396218e468709716ce5618.jpg","https://i.pinimg.com/236x/d5/b1/45/d5b145b09d6cbfc1e9cbdb55577b035e.jpg","https://i.pinimg.com/236x/c4/c3/6c/c4c36c8447bede8c32c5368c951b0707.jpg"],
    "icon_name":"0xf80e",
    "color":"#438D80",
    "email":"elshareya8@gmail.com",
    "password":"123456789",
    "profile":"https://i.pinimg.com/236x/6a/50/d9/6a50d95c92396218e468709716ce5618.jpg",
    "type":"charityCenter",
    "availability":"true",
    "open":"24 hours",
    "uid": "0POmD1TuCtP1Rc9Lg5TSdBSDvgD3"
  },

  {
    "id":"s1",
    "name":"مركز المنارة التخصصى لحديثى الولادة",
    "phone":["0222407059 ","01064343900"],
    "address":"ش سليم الاول 115-الزيتون-القاهرة",
    "location":"https://goo.gl/maps/v6UTRWtBvP9SUA7Q6",
    "late":30.11845720388082,
    "long":31.320442090164715,
    "image":["https://i.pinimg.com/564x/39/c1/66/39c1667670f5d1d92a6cc2339d5b24da.jpg","https://i.pinimg.com/236x/31/b1/40/31b1406ab9f7d941f1de9ab18b57d566.jpg","https://i.pinimg.com/236x/af/cd/fe/afcdfece9b200219580824fcb107a0e9.jpg"],
    "icon_name":"0xf7f2",
    "color":"#B1907F",
    "email":"elmanara@gmail.com",
    "password":"123456789",
    "profile":"https://i.pinimg.com/564x/39/c1/66/39c1667670f5d1d92a6cc2339d5b24da.jpg",
    "type": "specialCenter",
    "availability":"true",
    "open":"24 hours",
    "uid": "VmIP81ySW6Uz1wNFMyuNc0FP8NR2"
  },

  {
    "id":"s2",
    "name":"مركز الاسراء الطبى للاطفال و الحضانات لحديثى الولادة والمبتسرين",
    "phone":["0225072179","01100791413","01013030017"],
    "address":"القطعة 9076-ش9 المقطم-القاهرة",
    "location":"https://goo.gl/maps/T6V6p991wn7nFWFf6",
    "late":30.00814523303434,
    "long":31.30942515290951,
    "image":["https://i.pinimg.com/236x/6a/50/d9/6a50d95c92396218e468709716ce5618.jpg","https://i.pinimg.com/564x/b6/99/cf/b699cf95d58af208e6bbe2bf9e077515.jpg","https://i.pinimg.com/236x/86/5e/f5/865ef5dfb9b951d6bd7a65cc2b47393e.jpg"],
    "icon_name":"0xf7f2",
    "color":"#B1907F",
    "email":"elesraa@gmail.com",
    "password":"123456789",
    "profile":"https://i.pinimg.com/236x/6a/50/d9/6a50d95c92396218e468709716ce5618.jpg",
    "type": "specialCenter",
    "availability":"true",
    "open":"24 hours",
    "uid": "Pe2TRWHPP2ZVzmWOtHyyYrhPxo23"
  },
  {
    "id":"s3",
    "name":"د. شهيرة لويز - استشارى طب اطفال وحديثى الولادة",
    "phone":["0227548760 ","01005735915 ","01223322124 ","01275574553"],
    "address":"عمارات صقر قريش 16-المعادي الجديدة-المعادي-القاهرة",
    "location":"https://goo.gl/maps/qcSrSV7uB3h9BrBt5",
    "late":29.984387096528245,
    "long":31.284985726932454,
    "image":["https://i.pinimg.com/564x/06/c9/36/06c9368547acfdb19ea835ef7f67f1a2.jpg","https://i.pinimg.com/236x/3c/13/75/3c1375b10ea7d6975f3481e70108d2f7.jpg","https://i.pinimg.com/564x/3e/d7/b8/3ed7b87af4592207a60f7abc079059f3.jpg"],
    "icon_name":"0xf7f2",
    "color":"#B1907F",
    "email":"dr_shahera@gmail.com",
    "password":"123456789",
    "profile":"https://i.pinimg.com/564x/06/c9/36/06c9368547acfdb19ea835ef7f67f1a2.jpg",
    "type": "specialCenter",
    "availability":"true",
    "open":"24 hours",
    "uid": "kMmakDdKx7c72biRJOQHRLOX6bG3"
  },
  {
    "id":"s4",
    "name":"د. نشوة حسين العشرى - استشارى طب اطفال وحديثى الولادة والرضاعة الطبيعية",
    "address":"ععمارة شمس للتكيفات-ش 1/6 اللاسلكي-المعادي الجديدة-المعادي-القاهرة",
    "phone":["0225173511 ","01111419194"],
    "location":"https://goo.gl/maps/ALf3aLSRWbxmSrcK8",
    "late":29.973987571184374,
    "long":31.280541569317133,
    "image":["https://i.pinimg.com/236x/07/93/35/079335039d7d549b681d276959b327ca.jpg","https://i.pinimg.com/236x/79/10/fb/7910fb9997a023f81bb5049376d6452c.jpg","https://i.pinimg.com/564x/3e/d7/b8/3ed7b87af4592207a60f7abc079059f3.jpg"],
    "icon_name":"0xf7f2",
    "color":"#B1907F",
    "email":"dr_nashwa@gmail.com",
    "password":"123456789",
    "profile":"https://i.pinimg.com/236x/07/93/35/079335039d7d549b681d276959b327ca.jpg",
    "type": "specialCenter",
    "availability":"true",
    "open":"24 hours",
    "uid": "gqkUYCqFoERRkfeX01lZFNIrtSq2"
  },

  {
    "id":"s5",
    "name":"مركز حياة لرعاية حديثى الولادة والمبتسرين",
    "phone":["0403334507 ","0409117582 ","01227972287"],
    "address":" برج الطوخي- ش لالفي تقاطع 1 ش النحاس الدور 3-طنطا-الغربية",
    "location":"https://goo.gl/maps/Dux63CEhmmis5AwTA",
    "late":30.791830301685003,
    "long":30.994424184676273,
    "image":["https://i.pinimg.com/564x/a1/f4/68/a1f4684875bc3fcbc7112e1b81649ebe.jpg","https://i.pinimg.com/236x/9f/81/35/9f81350e939dac27ae2f1ce2a2855ba5.jpg","https://i.pinimg.com/236x/66/d4/f1/66d4f12cf31a103fa46e8e2cec58c3a3.jpg"],
    "icon_name":"0xf7f2",
    "color":"#B1907F",
    "email":"hayah@gmail.com",
    "password":"123456789",
    "profile":"https://i.pinimg.com/564x/a1/f4/68/a1f4684875bc3fcbc7112e1b81649ebe.jpg",
    "type": "specialCenter",
    "availability":"true",
    "open":"24 hours",
    "uid": "YZ58toU5t4bkL7G2x9FOKIi2xdV2"
  },

  {
    "id":"s6",
    "name":"المركز الطبى التخصصى للاطفال وحديثى الولادة",
    "phone":["0882333604  ","01005225218"],
    "address":"برج الشيماء-ميدان المحطة-الدور 2-حي شرق اسيوط",
    "location":"https://goo.gl/maps/39yoakmn6CfopnJK8",
    "late":27.179616933391195,
    "long":31.18842528824121,
    "image":["https://i.pinimg.com/236x/75/f7/b8/75f7b840ec270e3977a17000b2c76038.jpg","https://i.pinimg.com/236x/6a/50/d9/6a50d95c92396218e468709716ce5618.jpg","https://i.pinimg.com/236x/9b/6b/18/9b6b1868a1ddad33c688570257930cec.jpg"],
    "icon_name":"0xf7f2",
    "color":"#B1907F",
    "email":"elshaymaa@gmail.com",
    "password":"123456789",
    "profile":"https://i.pinimg.com/236x/75/f7/b8/75f7b840ec270e3977a17000b2c76038.jpg",
    "type": "specialCenter",
    "availability":"true",
    "open":"24 hours",
    "uid": "SuHHnQP1cwbSEhV86RhUzMOk9J82"
  },

  {
    "id":"s7",
    "name":"مركز براعم الطبى للأطفال و حديثى الولادة",
    "phone":"0623338888",
    "address":"برج رشيد - ميدان الفرز - السويس",
    "location":"https://goo.gl/maps/ibfxwy7gt6GshHWt5",
    "late":29.969750276822783,
    "long":32.54690387415968,
    "image":["https://i.pinimg.com/564x/6b/d5/98/6bd598d10120864d200a4fbf61db4527.jpg","https://i.pinimg.com/564x/a6/71/26/a671260636a9f0a35684001c42c46b39.jpg","https://i.pinimg.com/564x/e3/b2/6a/e3b26affad7ce9bf49ecdf6e27428b06.jpg"],
    "icon_name":"0xf7f2",
    "color":"#B1907F",
    "email":"baraem@gmail.com",
    "password":"123456789",
    "profile":"https://i.pinimg.com/564x/6b/d5/98/6bd598d10120864d200a4fbf61db4527.jpg",
    "type": "specialCenter",
    "availability":"true",
    "open":"24 hours",
    "uid": "7vBWt5no86UOWEH521AkgRtWhnL2"
  },
  {
    "id":"s8",
    "name":"مركز الرحمة للحضانات",
    "phone":"01100588650",
    "address":"ثان أسوان - أسوان",
    "location":"https://goo.gl/maps/qpNzoxyek8aKCK5s8",
    "late":24.083501111474934,
    "long":32.908320180083436,
    "image":["https://i.pinimg.com/236x/65/2a/da/652ada4e02e64214e3d51513a3649538.jpg","https://i.pinimg.com/236x/83/60/8b/83608bf1ebd24660122e2d231e5810cc.jpg","https://i.pinimg.com/236x/27/4f/33/274f3348f2edb78f1d0a3fe6b5eaa8be.jpg"],
    "icon_name":"0xf7f2",
    "color":"#B1907F",
    "email":"elrahma@gmail.com",
    "password":"123456789",
    "profile":"https://i.pinimg.com/236x/65/2a/da/652ada4e02e64214e3d51513a3649538.jpg",
    "type": "specialCenter",
    "availability":"true",
    "open":"24 hours",
    "uid": "Kw3liUWtNehp8cr4lD8nirodXnT2"
  },
  {
    "id":"s9",
    "name":"مركز ملك الرحمة للاطفال المبتسرين",
    "phone":"034812476",
    "address":"الاسقف، العطارين غرب، العطارين، الإسكندرية",
    "location":"https://goo.gl/maps/Dsj721zLjgF3x5Mz5",
    "late":31.195138747494525,
    "long":29.895463432412086,
    "image":["https://i.pinimg.com/236x/de/2a/97/de2a9796c865acac33cc2e152aa616b4.jpg","https://i.pinimg.com/236x/21/3e/3c/213e3c1968f06f1c76c6b2c80eb2ae0c.jpg","https://i.pinimg.com/236x/a9/6c/99/a96c9959c510c5141b9f44c0ed2bff89.jpg"],
    "icon_name":"0xf7f2",
    "color":"#B1907F",
    "email":"malak@gmail.com",
    "password":"123456789",
    "profile":"https://i.pinimg.com/236x/de/2a/97/de2a9796c865acac33cc2e152aa616b4.jpg",
    "type": "specialCenter",
    "availability":"true",
    "open":"24 hours",
    "uid": "e628fGktCAaldERdGnqK8k6EAl83"
  },

  {
    "id":"s10",
    "name":"مركز بنون للحضانات ورعايه الاطفال حديثي الولاده",
    "phone":"01010976361",
    "address":"قسم قنا، قنا",
    "location":"https://goo.gl/maps/7JuJBeDfntwZZdcu8",
    "late":26.162512978832407,
    "long":32.70772883253018,
    "image":["https://i.pinimg.com/564x/21/3e/3c/213e3c1968f06f1c76c6b2c80eb2ae0c.jpg","https://i.pinimg.com/564x/52/01/34/520134742df39ebec6ebfd34bd9a04b5.jpg","https://i.pinimg.com/564x/4e/e1/6a/4ee16aa64ee218d69b88ef8aba5ffb95.jpg"],
    "icon_name":"0xf7f2",
    "color":"#B1907F",
    "email":"banon@gmail.com",
    "password":"123456789",
    "profile":"https://i.pinimg.com/564x/21/3e/3c/213e3c1968f06f1c76c6b2c80eb2ae0c.jpg",
    "type": "specialCenter",
    "availability":"true",
    "open":"24 hours",
    "uid": "qRiaaVA3xudW3kjhwk0LWYtVup52"
  },
  {
    "id":"s11",
    "name":"مركز بداية للحضانات",
    "phone":"01028044112",
    "address":"بجوار مديريه التضامن الاجتماعى، البستان، قسم قنا، قنا",
    "location":"https://goo.gl/maps/NxXuqQXxiqwQpTGx5",
    "late":26.155217478741488,
    "long":32.718445361978084,
    "image":["https://i.pinimg.com/236x/af/cd/fe/afcdfece9b200219580824fcb107a0e9.jpg","https://i.pinimg.com/564x/b8/1e/3e/b81e3e51e75f01dbc6a71b98a4cfb9aa.jpg","https://i.pinimg.com/564x/5d/62/2a/5d622ac357018711a275f72656c95af8.jpg"],
    "icon_name":"0xf7f2",
    "color":"#B1907F",
    "email":"bedaya@gmail.com",
    "password":"123456789",
    "profile":"https://i.pinimg.com/236x/af/cd/fe/afcdfece9b200219580824fcb107a0e9.jpg",
    "type": "specialCenter",
    "availability":"true",
    "open":"24 hours",
    "uid": "EOHbcYWoUmdd0rYCkfu4dQ5xfnw2"
  },
  {
    "id":"s12",
    "name":"مركز بداية للحضانات و الرعاية المركزة للأطفال",
    "phone":"01066709234",
    "address":"المحطة، مدينة قطور، مركز قطور، الغربية",
    "location":"https://goo.gl/maps/XEGurGV5EGe9FWEB7",
    "late":30.969426544162097,
    "long":30.956893802970107,
    "image":["https://i.pinimg.com/564x/12/c0/8c/12c08cdc9a23dca1e652b15afc59d04d.jpg","https://i.pinimg.com/736x/6c/de/1c/6cde1c25bc330c38ea7c5ce3abb6d640.jpg","https://i.pinimg.com/564x/42/4c/e7/424ce7e3dfd17ae4bfe0d362f0f39cad.jpg"],
    "icon_name":"0xf7f2",
    "color":"#B1907F",
    "email":"bedaya1@gmail.com",
    "password":"123456789",
    "profile":"https://i.pinimg.com/564x/12/c0/8c/12c08cdc9a23dca1e652b15afc59d04d.jpg",
    "type": "specialCenter",
    "availability":"true",
    "open":"24 hours",
    "uid": "XY2vzGR1m2ZGOR9vvz10mlzVbzM2"
  },
  {
    "id":"s13",
    "name":"مركز بيبي كير للاطفال المبتسرين",
    "phone":"01069975238",
    "address":"الجامعي للنساء والولادة، مستشفى سوزان، طريق مصر اسوان الزراعي",
    "location":"https://goo.gl/maps/NUkmt4kUk9Vj2gfk6",
    "late":28.127016904218326,
    "long":30.738321432486682,
    "image":["https://i.pinimg.com/564x/6e/19/b1/6e19b1cdfb51519aa854a759dacadff0.jpg","https://i.pinimg.com/236x/53/08/ab/5308ab3477d13ae76c9c6400c45e5d04.jpg","https://i.pinimg.com/236x/7d/75/4d/7d754d0b88ee296f0f0760a8ad492a24.jpg"],
    "icon_name":"0xf7f2",
    "color":"#B1907F",
    "email":"baby@gmail.com",
    "password":"123456789",
    "profile":"https://i.pinimg.com/564x/6e/19/b1/6e19b1cdfb51519aa854a759dacadff0.jpg",
    "type": "specialCenter",
    "availability":"true",
    "open":"24 hours",
    "uid": "v1YKK5xKorUWBvs4pcSyj6d0xhf1"

  },
  {
    "id":"s14",
    "name":"حضانة اطفالنا للأطفال المبتسرين",
    "phone":"01151459689",
    "address":"هدى شعراوى، قسم المنيا، مركز المنيا، المنيا",
    "location":"https://goo.gl/maps/MjSuxDHZSMmpB4f88",
    "late":28.09259670375789,
    "long":30.757193832487538,
    "image":["https://i.pinimg.com/236x/b6/4d/2b/b64d2ba4e4fa7bc08a74349baca8d5de.jpg","https://i.pinimg.com/736x/6c/de/1c/6cde1c25bc330c38ea7c5ce3abb6d640.jpg","https://i.pinimg.com/564x/7c/43/bb/7c43bb05e0ea99c3c37719ab3b1da161.jpg"],
    "icon_name":"0xf7f2",
    "color":"#B1907F",
    "email":"atfalna@gmail.com",
    "password":"123456789",
    "profile":"https://i.pinimg.com/236x/b6/4d/2b/b64d2ba4e4fa7bc08a74349baca8d5de.jpg",
    "type": "specialCenter",
    "availability":"true",
    "open":"24 hours",
    "uid": "RBWB6xnf0OZiwNxRq3O5fIBrkDs2"

  },
  {
    "id":"s15",
    "name":"حضانة الشروق للاطفال حديثي الولادة",
    "phone":"01011401818",
    "address":"قسم المنيا، مركز المنيا،، قسم المنيا، المنيا",
    "location":"https://goo.gl/maps/yEfaANjUp7hnvE527",
    "late":28.089896612153858,
    "long":30.75502454475664,
    "image":["https://i.pinimg.com/564x/77/c1/58/77c1581eba42b94cbe7822a50b0cc7b7.jpg","https://i.pinimg.com/564x/39/c1/66/39c1667670f5d1d92a6cc2339d5b24da.jpg","https://i.pinimg.com/236x/ee/99/23/ee99233bfd46a30e70091bc5b66a293d.jpg"],
    "icon_name":"0xf7f2",
    "color":"#B1907F",
    "email":"elshorok@gmail.com",
    "password":"123456789",
    "profile":"https://i.pinimg.com/564x/77/c1/58/77c1581eba42b94cbe7822a50b0cc7b7.jpg",
    "type": "specialCenter",
    "availability":"true",
    "open":"24 hours",
    "uid": "paHh1Y8BYkRpRD3GaaAHmFgmUrp1"

  },
  {
    "id":"s16",
    "name":"مستشفي بيبي كير",
    "phone":"",
    "address":"السماد، فيصل، السويس",
    "location":"https://goo.gl/maps/nsiBVSU5pMtuKyD78",
    "late":30.00820385623884,
    "long":32.49109962691979,
    "image":["https://i.pinimg.com/236x/66/d4/f1/66d4f12cf31a103fa46e8e2cec58c3a3.jpg","https://i.pinimg.com/236x/96/d5/7c/96d57cb12e5fbc29176bf6457c6a0a29.jpg","https://i.pinimg.com/564x/72/e5/01/72e50139d7f08642fa92f6f2de6248a1.jpg"],
    "icon_name":"0xf7f2",
    "color":"#B1907F",
    "email":"baby1@gmail.com",
    "password":"123456789",
    "profile":"https://i.pinimg.com/236x/66/d4/f1/66d4f12cf31a103fa46e8e2cec58c3a3.jpg",
    "type": "specialCenter",
    "availability":"true",
    "open":"24 hours",
    "uid": "5jxoY7uZtkVhqeZbDrOQ6UWj1zS2"
  },
  {
    "id":"s17",
    "name":"المركز التخصصي لطب الاطفال",
    "phone":"01006093933",
    "address":"زاهر جلال، قسم مرسى مطروح، مطروح",
    "location":"https://g.page/PSCMatruoh?share",
    "late":31.353658949849013,
    "long":27.24338100296017,
    "image":["https://i.pinimg.com/564x/70/8a/f1/708af1ce4bda6a238df412ac5d90c422.jpg","https://i.pinimg.com/564x/f8/dd/1a/f8dd1ad308858e82890b536323fa5b6d.jpg","https://i.pinimg.com/564x/14/9b/70/149b705fbc9418246191d34dc5022b12.jpg"],
    "icon_name":"0xf7f2",
    "color":"#B1907F",
    "email":"eltakasosy@gmail.com",
    "password":"123456789",
    "profile":"https://i.pinimg.com/564x/70/8a/f1/708af1ce4bda6a238df412ac5d90c422.jpg",
    "type": "specialCenter",
    "availability":"true",
    "open":"24 hours",
    "uid": "j3XZS0eSDmUzdRI94O54sVUlcKW2"
  },

  {
    "id":"s18",
    "name":"مركز المنتصر للاطفال المبتسريين وعلاج الصفرة",
    "phone":"01068403359",
    "address":"الكرنك، الأقصر، محافظة الأقصر",
    "location":"https://goo.gl/maps/YV2VUQkMEcpk23B4A",
    "late":25.7262152611859,
    "long":32.660528697569546,
    "image":["https://i.pinimg.com/236x/44/d7/81/44d7818d7deea1c96fbf4b83c858e7e6.jpg","https://i.pinimg.com/236x/ee/99/23/ee99233bfd46a30e70091bc5b66a293d.jpg","https://i.pinimg.com/564x/47/1b/ae/471baed7fb4f47495a19449f18d66f9c.jpg"],
    "icon_name":"0xf7f2",
    "color":"#B1907F",
    "email":"elmontaser@gmail.com",
    "password":"123456789",
    "profile":"https://i.pinimg.com/236x/44/d7/81/44d7818d7deea1c96fbf4b83c858e7e6.jpg",
    "type": "specialCenter",
    "availability":"true",
    "open":"24 hours",
    "uid": "jcv4Wx80HJVF69B26cGkcWhEEEb2"
  },


  {
    "id":"s19",
    "name":"مركز حضانات حياتنا",
    "phone":"01099932630",
    "address":"بجوار حديقه الطفل، أحمد عرابي، جزيرة المساعدة، مركز الواسطى، محافظة بني سويف",
    "location":"https://g.page/hayatna-medical-center?share",
    "late":29.34672962089725,
    "long":31.209802932457983,
    "image":["https://i.pinimg.com/564x/e5/01/ee/e501ee5a41c4c372a690ce4479f1104b.jpg","https://i.pinimg.com/236x/16/cb/3d/16cb3d041997dbf245ece421a3affa1e.jpg","https://i.pinimg.com/564x/02/2b/c3/022bc3387665b76d11aab3faee3175cf.jpg"],
    "icon_name":"0xf7f2",
    "color":"#B1907F",
    "email":"hayatna@gmail.com",
    "password":"123456789",
    "profile":"https://i.pinimg.com/564x/e5/01/ee/e501ee5a41c4c372a690ce4479f1104b.jpg",
    "type": "specialCenter",
    "availability":"true",
    "open":"24 hours",
    "uid": "Y30ralnHb4SkQE7bTOOHdhlNDM33"
  }

]